{
    "EffectiveFlags": 281475043819552,
    "LocalIPAddress": null,
    "SetTemperatureZone1": 10,
    "SetTemperatureZone2": 20,
    "RoomTemperatureZone1": 21.5,
    "RoomTemperatureZone2": -39,
    "OperationMode": 2,
    "OperationModeZone1": 1,
    "OperationModeZone2": 2,
    "WeatherObservations": [
        {
            "Date": "2024-02-23T18:00:00",
            "Sunrise": "2024-02-23T06:59:00",
            "Sunset": "2024-02-23T17:30:00",
            "Condition": 176,
            "ID": 1501593816,
            "Humidity": 78,
            "Temperature": 5,
            "Icon": "wsymbol_0025_light_rain_showers_night",
            "ConditionName": "Patchy rain nearby",
            "Day": 5,
            "WeatherType": 0
        },
        {
            "Date": "2024-02-24T03:00:00",
            "Sunrise": "2024-02-24T06:57:00",
            "Sunset": "2024-02-24T17:31:00",
            "Condition": 176,
            "ID": 1502881667,
            "Humidity": 81,
            "Temperature": 2,
            "Icon": "wsymbol_0025_light_rain_showers_night",
            "ConditionName": "Patchy rain nearby",
            "Day": 5,
            "WeatherType": 2
        },
        {
            "Date": "2024-02-24T15:00:00",
            "Sunrise": "2024-02-24T06:57:00",
            "Sunset": "2024-02-24T17:31:00",
            "Condition": 176,
            "ID": 1502881671,
            "Humidity": 68,
            "Temperature": 7,
            "Icon": "wsymbol_0009_light_rain_showers",
            "ConditionName": "Patchy rain nearby",
            "Day": 6,
            "WeatherType": 1
        },
        {
            "Date": "2024-02-25T03:00:00",
            "Sunrise": "2024-02-25T06:55:00",
            "Sunset": "2024-02-25T17:33:00",
            "Condition": 113,
            "ID": 1504185459,
            "Humidity": 90,
            "Temperature": 3,
            "Icon": "wsymbol_0008_clear_sky_night",
            "ConditionName": "Clear/Sunny",
            "Day": 6,
            "WeatherType": 2
        }
    ],
    "ErrorMessage": null,
    "ErrorCode": 8000,
    "SetHeatFlowTemperatureZone1": 31,
    "SetHeatFlowTemperatureZone2": 20,
    "SetCoolFlowTemperatureZone1": 20,
    "SetCoolFlowTemperatureZone2": 20,
    "HCControlType": 1,
    "TankWaterTemperature": 53,
    "SetTankWaterTemperature": 53,
    "ForcedHotWaterMode": false,
    "UnitStatus": 0,
    "OutdoorTemperature": 7,
    "EcoHotWater": false,
    "Zone1Name": "Heatmiser",
    "Zone2Name": null,
    "HolidayMode": false,
    "ProhibitZone1": false,
    "ProhibitZone2": false,
    "ProhibitHotWater": true,
    "TemperatureIncrementOverride": 0,
    "IdleZone1": false,
    "IdleZone2": true,
    "DemandPercentage": 100,
    "DeviceID": 55125051,
    "DeviceType": 1,
    "LastCommunication": "2024-02-23T16:38:25.557",
    "NextCommunication": "2024-02-23T16:39:25.557",
    "Power": true,
    "HasPendingCommand": false,
    "Offline": false,
    "Scene": null,
    "SceneOwner": null
}